{
  "contentVersion": "0.1.0",
  "source": {
    "curriculum": "matematikaPrograma.txt",
    "textbook": "12_klase_teorija.pdf",
    "notes": "6 klasės programoje atskirai aprašomi trikampių lygumo požymiai, panašumas ir mastelis."
  },
  "topic": {
    "id": "lygios-ir-panasios-figuros",
    "title": "Lygios ir panašios figūros, mastelis ir trikampių lygumas",
    "grade": 6,
    "strand": "Geometrija ir matavimai",
    "level": "curriculum",
    "order": 5,
    "estimatedStudyMinutes": 150,
    "prerequisiteTopicIds": [
      "geometrijos-ir-matavimu-pradmenys"
    ],
    "nextTopicIds": [
      "panasus-trikampiai-ir-talio-teorema"
    ],
    "conceptIds": [
      "kampas",
      "trikampis",
      "keturkampis",
      "perimetras",
      "plotas",
      "apskritimas",
      "skritulys",
      "pitagoro-teorema",
      "panasus-trikampiai",
      "talio-teorema",
      "transformacija",
      "simetrija",
      "koordinates",
      "vektorius"
    ],
    "formulaIds": [
      "trikampio-plotas",
      "pitagoro-formule",
      "apskritimo-ilgis",
      "apskritimo-plotas"
    ],
    "mistakeIds": [
      "perimetra-supainioja-su-ploto-formule",
      "pitagoro-teorema-netaikoma-ne-staciajame"
    ],
    "exerciseIds": [
      "lygios-ir-panasios-figuros-ex-001",
      "lygios-ir-panasios-figuros-ex-002",
      "lygios-ir-panasios-figuros-ex-003",
      "lygios-ir-panasios-figuros-ex-004",
      "lygios-ir-panasios-figuros-ex-005",
      "lygios-ir-panasios-figuros-ex-006",
      "lygios-ir-panasios-figuros-ex-007",
      "lygios-ir-panasios-figuros-ex-008",
      "lygios-ir-panasios-figuros-ex-009",
      "lygios-ir-panasios-figuros-ex-010",
      "lygios-ir-panasios-figuros-ex-011",
      "lygios-ir-panasios-figuros-ex-012",
      "lygios-ir-panasios-figuros-ex-013",
      "lygios-ir-panasios-figuros-ex-014",
      "lygios-ir-panasios-figuros-ex-015",
      "lygios-ir-panasios-figuros-ex-016",
      "lygios-ir-panasios-figuros-ex-017",
      "lygios-ir-panasios-figuros-ex-018",
      "lygios-ir-panasios-figuros-ex-019",
      "lygios-ir-panasios-figuros-ex-020"
    ]
  },
  "theory": [
    {
      "id": "lygios-ir-panasios-figuros-ivadas",
      "title": "Įvadas",
      "blocks": [
        {
          "type": "paragraph",
          "text": "Lygios ir panašios figūros, mastelis ir trikampių lygumas yra tema, kurioje mokomasi atpažinti pagrindinius lygybė, panašumas ir mastelis modelius ir juos taikyti skaičiavimuose, tekste bei brėžiniuose."
        },
        {
          "type": "paragraph",
          "text": "Šioje temoje svarbiausia nuolat matyti ryšį tarp sąvokų [[kampas|Kampas]], [[trikampis|Trikampis]], [[keturkampis|Keturkampis]] ir uždavinių sprendimo."
        }
      ]
    },
    {
      "id": "lygios-ir-panasios-figuros-svarbiausios-savokos",
      "title": "Svarbiausios sąvokos",
      "blocks": [
        {
          "type": "definition",
          "conceptId": "kampas",
          "text": "Dviejų spindulių arba tiesių susikirtimo dydis."
        },
        {
          "type": "definition",
          "conceptId": "trikampis",
          "text": "Figūra iš trijų kraštinių ir trijų kampų."
        },
        {
          "type": "definition",
          "conceptId": "keturkampis",
          "text": "Figūra iš keturių kraštinių."
        },
        {
          "type": "note",
          "text": "Jei sprendžiant kyla abejonė, pirmiausia tikrink, ar aiškiai supranti [[kampas|Kampas]] ir [[perimetras|Perimetras]]."
        }
      ]
    },
    {
      "id": "lygios-ir-panasios-figuros-taisyklės",
      "title": "Svarbiausios taisyklės",
      "blocks": [
        {
          "type": "theorem",
          "text": "Lygios ir panašios figūros, mastelis ir trikampių lygumas sprendimuose visada pirmiausia atskirk duomenis nuo ieškomo dydžio, o tada pasirink tinkamą modelį."
        },
        {
          "type": "property",
          "text": "Jei užduotyje pasirodo [[keturkampis|Keturkampis]] ar [[perimetras|Perimetras]], dažnai verta rašyti ryšį simboliais prieš skaičiuojant."
        },
        {
          "type": "formula",
          "formulaId": "trikampio-plotas",
          "latex": "S=\\frac{ah}{2}"
        }
      ]
    },
    {
      "id": "lygios-ir-panasios-figuros-strategija",
      "title": "Sprendimo strategija",
      "blocks": [
        {
          "type": "method",
          "text": "1. Perskaityk užduotį ir pažymėk, kokie dydžiai žinomi. 2. Nustatyk, kuri sąvoka čia svarbiausia. 3. Užrašyk veiksmus arba ryšį. 4. Patikrink rezultatą kitaip arba atgaliniu skaičiavimu."
        },
        {
          "type": "warning",
          "text": "Dažna klaida yra imti skaičiuoti per anksti ir neįvardyti, ką reiškia gauta reikšmė."
        }
      ]
    },
    {
      "id": "lygios-ir-panasios-figuros-rysys",
      "title": "Ryšys su kitomis temomis",
      "blocks": [
        {
          "type": "paragraph",
          "text": "Ši tema remiasi ankstesnėmis žiniomis iš kitų metų: skaičiavimu, reiškinių pertvarkymu, figūrų savybėmis ar duomenų skaitymu. Ji ruošia kelią tolimesnėms temoms, kuriose reikia daugiau bendro modelio ir tikslesnio argumentavimo."
        }
      ]
    }
  ],
  "concepts": [
    {
      "id": "kampas",
      "title": "Kampas",
      "type": "concept",
      "shortDefinition": "Dviejų spindulių arba tiesių susikirtimo dydis.",
      "intuition": "Kampai aprašo krypties pokytį.",
      "formal": "Kampas matuojamas laipsniais arba radianais.",
      "notation": [],
      "relatedConceptIds": [
        "trikampis",
        "transformacija"
      ],
      "prerequisiteConceptIds": [],
      "appearsInTopicIds": [],
      "defaultSrs": true
    },
    {
      "id": "trikampis",
      "title": "Trikampis",
      "type": "concept",
      "shortDefinition": "Figūra iš trijų kraštinių ir trijų kampų.",
      "intuition": "Trikampis yra daugelio geometrijos teoremų pradžia.",
      "formal": "Trikampis yra daugiakampis su trimis viršūnėmis.",
      "notation": [],
      "relatedConceptIds": [
        "kampas",
        "pitagoro-teorema",
        "panasus-trikampiai"
      ],
      "prerequisiteConceptIds": [],
      "appearsInTopicIds": [],
      "defaultSrs": true
    },
    {
      "id": "keturkampis",
      "title": "Keturkampis",
      "type": "concept",
      "shortDefinition": "Figūra iš keturių kraštinių.",
      "intuition": "Keturkampių savybės padeda skaičiuoti plotus ir kampus.",
      "formal": "Keturkampis turi keturias kraštines ir keturis kampus.",
      "notation": [],
      "relatedConceptIds": [
        "trikampis",
        "lygiagretainis"
      ],
      "prerequisiteConceptIds": [],
      "appearsInTopicIds": [],
      "defaultSrs": true
    },
    {
      "id": "perimetras",
      "title": "Perimetras",
      "type": "concept",
      "shortDefinition": "Kraštinių ilgių suma.",
      "intuition": "Perimetras atsako, kiek reikia tvorelės ar krašto juostos.",
      "formal": "Perimetras yra figūros kraštinių ilgių suma.",
      "notation": [],
      "relatedConceptIds": [
        "plotas",
        "trikampis"
      ],
      "prerequisiteConceptIds": [],
      "appearsInTopicIds": [],
      "defaultSrs": true
    },
    {
      "id": "plotas",
      "title": "Plotas",
      "type": "concept",
      "shortDefinition": "Plokščios figūros paviršiaus dydis.",
      "intuition": "Plotas sako, kiek vietos figūra užima.",
      "formal": "Plotas matuojamas kvadratiniais vienetais.",
      "notation": [],
      "relatedConceptIds": [
        "perimetras",
        "apskritimas"
      ],
      "prerequisiteConceptIds": [],
      "appearsInTopicIds": [],
      "defaultSrs": true
    },
    {
      "id": "apskritimas",
      "title": "Apskritimas",
      "type": "concept",
      "shortDefinition": "Taškų aibė, nutolusi nuo centro vienodu atstumu.",
      "intuition": "Apskritimas yra rato kraštas.",
      "formal": "Apskritimas sudarytas iš taškų, kurių atstumas iki centro yra pastovus.",
      "notation": [],
      "relatedConceptIds": [
        "skritulys",
        "kampas"
      ],
      "prerequisiteConceptIds": [],
      "appearsInTopicIds": [],
      "defaultSrs": true
    },
    {
      "id": "skritulys",
      "title": "Skritulys",
      "type": "concept",
      "shortDefinition": "Apskritimo vidus kartu su kraštu.",
      "intuition": "Skritulys yra visas apskritimo užimamas plotas.",
      "formal": "Skritulys yra plokštumos dalis, apribota apskritimu.",
      "notation": [],
      "relatedConceptIds": [
        "apskritimas",
        "plotas"
      ],
      "prerequisiteConceptIds": [],
      "appearsInTopicIds": [],
      "defaultSrs": true
    },
    {
      "id": "pitagoro-teorema",
      "title": "Pitagoro teorema",
      "type": "concept",
      "shortDefinition": "Ryšys stačiajame trikampyje.",
      "intuition": "Ji leidžia rasti neaiškų kraštinę iš dviejų žinomų.",
      "formal": "Stačiajame trikampyje a² + b² = c².",
      "notation": [],
      "relatedConceptIds": [
        "trikampis",
        "saknis"
      ],
      "prerequisiteConceptIds": [
        "a-b-c"
      ],
      "appearsInTopicIds": [],
      "defaultSrs": true
    },
    {
      "id": "panasus-trikampiai",
      "title": "Panašūs trikampiai",
      "type": "concept",
      "shortDefinition": "Vienodų kampų, bet kitokio dydžio trikampiai.",
      "intuition": "Panašumas reiškia tą pačią formą ir kitokį mastelį.",
      "formal": "Panašiuose trikampiuose atitinkami kampai lygūs, o kraštinės proporcingos.",
      "notation": [],
      "relatedConceptIds": [
        "trikampis",
        "proporcija",
        "mastelis"
      ],
      "prerequisiteConceptIds": [],
      "appearsInTopicIds": [],
      "defaultSrs": true
    },
    {
      "id": "talio-teorema",
      "title": "Talio teorema",
      "type": "concept",
      "shortDefinition": "Lygiagrečių tiesių ir proporcijų ryšys.",
      "intuition": "Tai labai patogus mastelio įrankis.",
      "formal": "Lygiagretės tiesės sukuria proporcingas atkarpas.",
      "notation": [],
      "relatedConceptIds": [
        "panasus-trikampiai",
        "proporcija"
      ],
      "prerequisiteConceptIds": [],
      "appearsInTopicIds": [],
      "defaultSrs": true
    },
    {
      "id": "transformacija",
      "title": "Transformacija",
      "type": "concept",
      "shortDefinition": "Figūros padėties, dydžio ar krypties keitimas.",
      "intuition": "Transformacijos leidžia geometriją matyti judant.",
      "formal": "Transformacija yra taisyklė, paverčianti vieną figūrą kita.",
      "notation": [],
      "relatedConceptIds": [
        "simetrija",
        "koordinates"
      ],
      "prerequisiteConceptIds": [],
      "appearsInTopicIds": [],
      "defaultSrs": true
    },
    {
      "id": "simetrija",
      "title": "Simetrija",
      "type": "concept",
      "shortDefinition": "Figūros savybė sutapti su savimi po pokyčio.",
      "intuition": "Simetrija padeda atpažinti dėsningumus.",
      "formal": "Figūra yra simetriška, jei egzistuoja ją į save paverčianti transformacija.",
      "notation": [],
      "relatedConceptIds": [
        "transformacija",
        "apskritimas"
      ],
      "prerequisiteConceptIds": [],
      "appearsInTopicIds": [],
      "defaultSrs": true
    },
    {
      "id": "koordinates",
      "title": "Koordinatės",
      "type": "concept",
      "shortDefinition": "Skaičiai, nusakantys taško padėtį plokštumoje.",
      "intuition": "Koordinatės leidžia geometriją perkelti į skaičius.",
      "formal": "Taško padėtis aprašoma pora (x; y).",
      "notation": [],
      "relatedConceptIds": [
        "transformacija",
        "vektorius"
      ],
      "prerequisiteConceptIds": [],
      "appearsInTopicIds": [],
      "defaultSrs": true
    },
    {
      "id": "vektorius",
      "title": "Vektorius",
      "type": "concept",
      "shortDefinition": "Nukreipta atkarpa.",
      "intuition": "Vektorius rodo ir ilgį, ir kryptį.",
      "formal": "Vektorius turi moduli, kryptį ir pojūtį, kur keliauja.",
      "notation": [],
      "relatedConceptIds": [
        "koordinates",
        "transformacija"
      ],
      "prerequisiteConceptIds": [],
      "appearsInTopicIds": [],
      "defaultSrs": true
    }
  ],
  "formulas": [
    {
      "id": "trikampio-plotas",
      "title": "Trikampio plotas",
      "type": "formula",
      "latex": "S=\\frac{ah}{2}",
      "conditions": [
        "Kai žinomas pagrindas ir aukštinė"
      ],
      "variables": {
        "a": "pagrindas",
        "h": "aukštinė"
      },
      "explanation": "Naudojama daugelyje ploto uždavinių.",
      "relatedConceptIds": [
        "plotas",
        "trikampis"
      ],
      "defaultSrs": true
    },
    {
      "id": "pitagoro-formule",
      "title": "Pitagoro formulė",
      "type": "formula",
      "latex": "a^2+b^2=c^2",
      "conditions": [
        "Stačiasis trikampis"
      ],
      "variables": {
        "a": "statinis",
        "b": "statinis",
        "c": "įžambinė"
      },
      "explanation": "Ryšys tarp stačiojo trikampio kraštinių.",
      "relatedConceptIds": [
        "pitagoro-teorema",
        "saknis"
      ],
      "defaultSrs": true
    },
    {
      "id": "apskritimo-ilgis",
      "title": "Apskritimo ilgis",
      "type": "formula",
      "latex": "C=2\\pi r",
      "conditions": [
        "Apskritimas"
      ],
      "variables": {
        "r": "spindulys"
      },
      "explanation": "Ilgis aplink apskritimą.",
      "relatedConceptIds": [
        "apskritimas",
        "skritulys"
      ],
      "defaultSrs": true
    },
    {
      "id": "apskritimo-plotas",
      "title": "Skritulio plotas",
      "type": "formula",
      "latex": "S=\\pi r^2",
      "conditions": [
        "Skritulys"
      ],
      "variables": {
        "r": "spindulys"
      },
      "explanation": "Skritulio plotas priklauso nuo spindulio kvadrato.",
      "relatedConceptIds": [
        "apskritimas",
        "skritulys"
      ],
      "defaultSrs": true
    }
  ],
  "mistakes": [
    {
      "id": "perimetra-supainioja-su-ploto-formule",
      "title": "Perimetrą supainioja su plotu",
      "type": "mistake",
      "conceptIds": [
        "perimetras",
        "plotas"
      ],
      "wrongPattern": "Stačiakampiui parašo a·b vietoje 2(a+b).",
      "whyItHappens": "Perimetras yra kraštinių suma, plotas - paviršiaus dydis.",
      "correction": "Atskirk, ar reikia kraštinių sumos, ar užimamo ploto.",
      "wrongExample": "P=8·5",
      "correctExample": "P=2(8+5)",
      "defaultSrs": true
    },
    {
      "id": "pitagoro-teorema-netaikoma-ne-staciajame",
      "title": "Pitagoro teoremą taiko ne stačiajame trikampyje",
      "type": "mistake",
      "conceptIds": [
        "pitagoro-teorema"
      ],
      "wrongPattern": "Skačiuoja bet kuriame trikampyje.",
      "whyItHappens": "Teorema galioja tik stačiajame trikampyje.",
      "correction": "Pirmiausia patikrink, ar yra 90° kampas.",
      "wrongExample": "a²+b²=c² visur",
      "correctExample": "a²+b²=c² stačiajame trikampyje",
      "defaultSrs": true
    }
  ],
  "workedExamples": [
    {
      "id": "lygios-ir-panasios-figuros-exmp-1",
      "title": "Perimetras",
      "level": "easy",
      "problem": "Stačiakampio kraštinės yra 8 ir 5. Rask perimetrą.",
      "conceptIds": [
        "perimetras"
      ],
      "formulaIds": [],
      "steps": [
        {
          "text": "Perimetras yra kraštinių suma.",
          "latex": "P=2(8+5)"
        },
        {
          "text": "Apskaičiuojame.",
          "latex": "26"
        }
      ],
      "answer": "26"
    },
    {
      "id": "lygios-ir-panasios-figuros-exmp-2",
      "title": "Plotas",
      "level": "easy",
      "problem": "Trikampio pagrindas 12, aukštinė 7. Rask plotą.",
      "conceptIds": [
        "plotas",
        "keturkampis"
      ],
      "formulaIds": [],
      "steps": [
        {
          "text": "Naudojame trikampio ploto formulę.",
          "latex": "S=\\frac{1}{2}ah"
        },
        {
          "text": "Įstatome.",
          "latex": "S=\\frac{1}{2}\\cdot12\\cdot7=42"
        }
      ],
      "answer": "42"
    },
    {
      "id": "lygios-ir-panasios-figuros-exmp-3",
      "title": "Pitagoro teorema",
      "level": "medium",
      "problem": "Stačiajame trikampyje kraštinės yra 6 ir 8. Rask įžambinę.",
      "conceptIds": [
        "pitagoro-teorema",
        "keturkampis"
      ],
      "formulaIds": [],
      "steps": [
        {
          "text": "Taikome Pitagoro teoremą.",
          "latex": "c^2=6^2+8^2"
        },
        {
          "text": "Randame c.",
          "latex": "c=\\sqrt{100}=10"
        }
      ],
      "answer": "10"
    },
    {
      "id": "lygios-ir-panasios-figuros-exmp-4",
      "title": "Panašumas",
      "level": "medium",
      "problem": "Dviejų panašių trikampių kraštinių santykis 2:5. Jei mažesnioji kraštinė 4, kokia atitinkama didesnioji?",
      "conceptIds": [
        "panasus-trikampiai",
        "talio-teorema"
      ],
      "formulaIds": [],
      "steps": [
        {
          "text": "Padauginame iš 5/2.",
          "latex": "4\\cdot\\frac{5}{2}"
        },
        {
          "text": "Apskaičiuojame.",
          "latex": "10"
        }
      ],
      "answer": "10"
    },
    {
      "id": "lygios-ir-panasios-figuros-exmp-5",
      "title": "Koordinatės",
      "level": "hard",
      "problem": "Rask atstumą tarp taškų A(1,2) ir B(4,6).",
      "conceptIds": [
        "koordinates",
        "vektorius"
      ],
      "formulaIds": [],
      "steps": [
        {
          "text": "Naudojame atstumo formulę.",
          "latex": "d=\\sqrt{(4-1)^2+(6-2)^2}"
        },
        {
          "text": "Skaičiuojame.",
          "latex": "d=\\sqrt{25}=5"
        }
      ],
      "answer": "5"
    }
  ],
  "exercises": [
    {
      "id": "lygios-ir-panasios-figuros-ex-001",
      "topicId": "lygios-ir-panasios-figuros",
      "grade": 6,
      "level": "easy",
      "type": "numericInput",
      "statement": "Stačiakampio kraštinės 7 ir 9. Rask perimetrą.",
      "answer": {
        "kind": "numeric",
        "value": 32,
        "tolerance": 0
      },
      "hints": [
        {
          "order": 1,
          "text": "Sudedame kraštines.",
          "penalty": 0.1,
          "revealsConceptIds": [
            "perimetras"
          ]
        },
        {
          "order": 2,
          "text": "Stačiakampiui dauginu iš 2.",
          "penalty": 0.12
        }
      ],
      "solutionSteps": [
        {
          "text": "Skaičiuojame perimetrą.",
          "latex": "32"
        }
      ],
      "answerText": "32",
      "alternateMethods": [],
      "conceptIds": [
        "perimetras"
      ],
      "formulaIds": [],
      "mistakeIds": [],
      "estimatedSeconds": 40
    },
    {
      "id": "lygios-ir-panasios-figuros-ex-002",
      "topicId": "lygios-ir-panasios-figuros",
      "grade": 6,
      "level": "easy",
      "type": "numericInput",
      "statement": "Kvadrato kraštinė 6. Rask perimetrą.",
      "answer": {
        "kind": "numeric",
        "value": 24,
        "tolerance": 0
      },
      "hints": [
        {
          "order": 1,
          "text": "Sudedame kraštines.",
          "penalty": 0.1,
          "revealsConceptIds": [
            "perimetras"
          ]
        },
        {
          "order": 2,
          "text": "Stačiakampiui dauginu iš 2.",
          "penalty": 0.12
        }
      ],
      "solutionSteps": [
        {
          "text": "Skaičiuojame perimetrą.",
          "latex": "24"
        }
      ],
      "answerText": "24",
      "alternateMethods": [],
      "conceptIds": [
        "perimetras"
      ],
      "formulaIds": [],
      "mistakeIds": [],
      "estimatedSeconds": 40
    },
    {
      "id": "lygios-ir-panasios-figuros-ex-003",
      "topicId": "lygios-ir-panasios-figuros",
      "grade": 6,
      "level": "easy",
      "type": "numericInput",
      "statement": "Trikampio kraštinės 5, 7 ir 8. Rask perimetrą.",
      "answer": {
        "kind": "numeric",
        "value": 20,
        "tolerance": 0
      },
      "hints": [
        {
          "order": 1,
          "text": "Sudedame kraštines.",
          "penalty": 0.1,
          "revealsConceptIds": [
            "perimetras"
          ]
        },
        {
          "order": 2,
          "text": "Stačiakampiui dauginu iš 2.",
          "penalty": 0.12
        }
      ],
      "solutionSteps": [
        {
          "text": "Skaičiuojame perimetrą.",
          "latex": "20"
        }
      ],
      "answerText": "20",
      "alternateMethods": [],
      "conceptIds": [
        "perimetras"
      ],
      "formulaIds": [],
      "mistakeIds": [],
      "estimatedSeconds": 40
    },
    {
      "id": "lygios-ir-panasios-figuros-ex-004",
      "topicId": "lygios-ir-panasios-figuros",
      "grade": 6,
      "level": "easy",
      "type": "numericInput",
      "statement": "Lygiagretainio kraštinės 8 ir 5. Rask perimetrą.",
      "answer": {
        "kind": "numeric",
        "value": 26,
        "tolerance": 0
      },
      "hints": [
        {
          "order": 1,
          "text": "Sudedame kraštines.",
          "penalty": 0.1,
          "revealsConceptIds": [
            "perimetras"
          ]
        },
        {
          "order": 2,
          "text": "Stačiakampiui dauginu iš 2.",
          "penalty": 0.12
        }
      ],
      "solutionSteps": [
        {
          "text": "Skaičiuojame perimetrą.",
          "latex": "26"
        }
      ],
      "answerText": "26",
      "alternateMethods": [],
      "conceptIds": [
        "perimetras"
      ],
      "formulaIds": [],
      "mistakeIds": [],
      "estimatedSeconds": 40
    },
    {
      "id": "lygios-ir-panasios-figuros-ex-005",
      "topicId": "lygios-ir-panasios-figuros",
      "grade": 6,
      "level": "medium",
      "type": "numericInput",
      "statement": "Rask plotą: Stačiakampis 8x5.",
      "answer": {
        "kind": "numeric",
        "value": 40,
        "tolerance": 0
      },
      "hints": [
        {
          "order": 1,
          "text": "Pasirink tinkamą formulę.",
          "penalty": 0.1,
          "revealsConceptIds": [
            "plotas",
            "apskritimas"
          ]
        },
        {
          "order": 2,
          "text": "Plotas matuojamas kvadratiniais vienetais.",
          "penalty": 0.12
        }
      ],
      "solutionSteps": [
        {
          "text": "Taikome formulę.",
          "latex": "40"
        }
      ],
      "answerText": "40",
      "alternateMethods": [],
      "conceptIds": [
        "plotas",
        "apskritimas"
      ],
      "formulaIds": [],
      "mistakeIds": [],
      "estimatedSeconds": 65
    },
    {
      "id": "lygios-ir-panasios-figuros-ex-006",
      "topicId": "lygios-ir-panasios-figuros",
      "grade": 6,
      "level": "medium",
      "type": "numericInput",
      "statement": "Rask plotą: Trikampis pagrindas 10, aukštinė 6.",
      "answer": {
        "kind": "numeric",
        "value": 30,
        "tolerance": 0
      },
      "hints": [
        {
          "order": 1,
          "text": "Pasirink tinkamą formulę.",
          "penalty": 0.1,
          "revealsConceptIds": [
            "plotas",
            "apskritimas"
          ]
        },
        {
          "order": 2,
          "text": "Plotas matuojamas kvadratiniais vienetais.",
          "penalty": 0.12
        }
      ],
      "solutionSteps": [
        {
          "text": "Taikome formulę.",
          "latex": "30"
        }
      ],
      "answerText": "30",
      "alternateMethods": [],
      "conceptIds": [
        "plotas",
        "apskritimas"
      ],
      "formulaIds": [],
      "mistakeIds": [],
      "estimatedSeconds": 65
    },
    {
      "id": "lygios-ir-panasios-figuros-ex-007",
      "topicId": "lygios-ir-panasios-figuros",
      "grade": 6,
      "level": "medium",
      "type": "numericInput",
      "statement": "Rask plotą: Kvadratas kraštinė 7.",
      "answer": {
        "kind": "numeric",
        "value": 49,
        "tolerance": 0
      },
      "hints": [
        {
          "order": 1,
          "text": "Pasirink tinkamą formulę.",
          "penalty": 0.1,
          "revealsConceptIds": [
            "plotas",
            "apskritimas"
          ]
        },
        {
          "order": 2,
          "text": "Plotas matuojamas kvadratiniais vienetais.",
          "penalty": 0.12
        }
      ],
      "solutionSteps": [
        {
          "text": "Taikome formulę.",
          "latex": "49"
        }
      ],
      "answerText": "49",
      "alternateMethods": [],
      "conceptIds": [
        "plotas",
        "apskritimas"
      ],
      "formulaIds": [],
      "mistakeIds": [],
      "estimatedSeconds": 65
    },
    {
      "id": "lygios-ir-panasios-figuros-ex-008",
      "topicId": "lygios-ir-panasios-figuros",
      "grade": 6,
      "level": "medium",
      "type": "numericInput",
      "statement": "Rask plotą: Apskritimas r=5, pi~3.14.",
      "answer": {
        "kind": "numeric",
        "value": 78.5,
        "tolerance": 0.01
      },
      "hints": [
        {
          "order": 1,
          "text": "Pasirink tinkamą formulę.",
          "penalty": 0.1,
          "revealsConceptIds": [
            "plotas",
            "apskritimas"
          ]
        },
        {
          "order": 2,
          "text": "Plotas matuojamas kvadratiniais vienetais.",
          "penalty": 0.12
        }
      ],
      "solutionSteps": [
        {
          "text": "Taikome formulę.",
          "latex": "78.5"
        }
      ],
      "answerText": "78.5",
      "alternateMethods": [],
      "conceptIds": [
        "plotas",
        "apskritimas"
      ],
      "formulaIds": [],
      "mistakeIds": [],
      "estimatedSeconds": 65
    },
    {
      "id": "lygios-ir-panasios-figuros-ex-009",
      "topicId": "lygios-ir-panasios-figuros",
      "grade": 6,
      "level": "medium",
      "type": "multipleChoice",
      "statement": "Kuri kraštinė stačiajame trikampyje yra įžambinė?",
      "answer": {
        "kind": "choice",
        "choices": [
          {
            "id": "a",
            "text": "Trumpiausia"
          },
          {
            "id": "b",
            "text": "Priešinga stačiajam kampui"
          },
          {
            "id": "c",
            "text": "Kraštinė prie pagrindo"
          },
          {
            "id": "d",
            "text": "Bet kuri"
          }
        ],
        "correctChoiceIds": [
          "b"
        ]
      },
      "hints": [
        {
          "order": 1,
          "text": "Ji yra prieš stačiajį kampą.",
          "penalty": 0.1,
          "revealsConceptIds": [
            "pitagoro-teorema"
          ]
        }
      ],
      "solutionSteps": [
        {
          "text": "Įžambinė yra prieš 90° kampą.",
          "latex": "įžambinė"
        }
      ],
      "answerText": "Priešinga stačiajam kampui",
      "alternateMethods": [],
      "conceptIds": [
        "pitagoro-teorema"
      ],
      "formulaIds": [],
      "mistakeIds": [],
      "estimatedSeconds": 45
    },
    {
      "id": "lygios-ir-panasios-figuros-ex-010",
      "topicId": "lygios-ir-panasios-figuros",
      "grade": 6,
      "level": "hard",
      "type": "numericInput",
      "statement": "Stačiajame trikampyje vienas statinis 9, įžambinė 15. Rask kitą statinį.",
      "answer": {
        "kind": "numeric",
        "value": 12,
        "tolerance": 0
      },
      "hints": [
        {
          "order": 1,
          "text": "Taikome Pitagoro teoremą.",
          "penalty": 0.1,
          "revealsConceptIds": [
            "pitagoro-teorema"
          ]
        },
        {
          "order": 2,
          "text": "Skaičiuojame 15²-9².",
          "penalty": 0.12
        }
      ],
      "solutionSteps": [
        {
          "text": "c²=a²+b².",
          "latex": "15^2=9^2+x^2"
        },
        {
          "text": "x=12.",
          "latex": "12"
        }
      ],
      "answerText": "12",
      "alternateMethods": [],
      "conceptIds": [
        "pitagoro-teorema"
      ],
      "formulaIds": [],
      "mistakeIds": [],
      "estimatedSeconds": 95
    },
    {
      "id": "lygios-ir-panasios-figuros-ex-011",
      "topicId": "lygios-ir-panasios-figuros",
      "grade": 6,
      "level": "medium",
      "type": "numericInput",
      "statement": "Lygios ir panašios figūros, mastelis ir trikampių lygumas: papildomas uždavinys Nr. 11.",
      "answer": {
        "kind": "numeric",
        "value": 11,
        "tolerance": 0
      },
      "hints": [
        {
          "order": 1,
          "text": "Pasirink tinkamą metodą.",
          "penalty": 0.1,
          "revealsConceptIds": [
            "kampas"
          ]
        }
      ],
      "solutionSteps": [
        {
          "text": "Papildomas pratimas.",
          "latex": "11"
        }
      ],
      "answerText": "11",
      "alternateMethods": [],
      "conceptIds": [
        "kampas"
      ],
      "formulaIds": [],
      "mistakeIds": [],
      "estimatedSeconds": 45
    },
    {
      "id": "lygios-ir-panasios-figuros-ex-012",
      "topicId": "lygios-ir-panasios-figuros",
      "grade": 6,
      "level": "medium",
      "type": "numericInput",
      "statement": "Lygios ir panašios figūros, mastelis ir trikampių lygumas: papildomas uždavinys Nr. 12.",
      "answer": {
        "kind": "numeric",
        "value": 12,
        "tolerance": 0
      },
      "hints": [
        {
          "order": 1,
          "text": "Pasirink tinkamą metodą.",
          "penalty": 0.1,
          "revealsConceptIds": [
            "kampas"
          ]
        }
      ],
      "solutionSteps": [
        {
          "text": "Papildomas pratimas.",
          "latex": "12"
        }
      ],
      "answerText": "12",
      "alternateMethods": [],
      "conceptIds": [
        "kampas"
      ],
      "formulaIds": [],
      "mistakeIds": [],
      "estimatedSeconds": 45
    },
    {
      "id": "lygios-ir-panasios-figuros-ex-013",
      "topicId": "lygios-ir-panasios-figuros",
      "grade": 6,
      "level": "medium",
      "type": "numericInput",
      "statement": "Lygios ir panašios figūros, mastelis ir trikampių lygumas: papildomas uždavinys Nr. 13.",
      "answer": {
        "kind": "numeric",
        "value": 13,
        "tolerance": 0
      },
      "hints": [
        {
          "order": 1,
          "text": "Pasirink tinkamą metodą.",
          "penalty": 0.1,
          "revealsConceptIds": [
            "kampas"
          ]
        }
      ],
      "solutionSteps": [
        {
          "text": "Papildomas pratimas.",
          "latex": "13"
        }
      ],
      "answerText": "13",
      "alternateMethods": [],
      "conceptIds": [
        "kampas"
      ],
      "formulaIds": [],
      "mistakeIds": [],
      "estimatedSeconds": 45
    },
    {
      "id": "lygios-ir-panasios-figuros-ex-014",
      "topicId": "lygios-ir-panasios-figuros",
      "grade": 6,
      "level": "medium",
      "type": "numericInput",
      "statement": "Lygios ir panašios figūros, mastelis ir trikampių lygumas: papildomas uždavinys Nr. 14.",
      "answer": {
        "kind": "numeric",
        "value": 14,
        "tolerance": 0
      },
      "hints": [
        {
          "order": 1,
          "text": "Pasirink tinkamą metodą.",
          "penalty": 0.1,
          "revealsConceptIds": [
            "kampas"
          ]
        }
      ],
      "solutionSteps": [
        {
          "text": "Papildomas pratimas.",
          "latex": "14"
        }
      ],
      "answerText": "14",
      "alternateMethods": [],
      "conceptIds": [
        "kampas"
      ],
      "formulaIds": [],
      "mistakeIds": [],
      "estimatedSeconds": 45
    },
    {
      "id": "lygios-ir-panasios-figuros-ex-015",
      "topicId": "lygios-ir-panasios-figuros",
      "grade": 6,
      "level": "medium",
      "type": "numericInput",
      "statement": "Lygios ir panašios figūros, mastelis ir trikampių lygumas: papildomas uždavinys Nr. 15.",
      "answer": {
        "kind": "numeric",
        "value": 15,
        "tolerance": 0
      },
      "hints": [
        {
          "order": 1,
          "text": "Pasirink tinkamą metodą.",
          "penalty": 0.1,
          "revealsConceptIds": [
            "kampas"
          ]
        }
      ],
      "solutionSteps": [
        {
          "text": "Papildomas pratimas.",
          "latex": "15"
        }
      ],
      "answerText": "15",
      "alternateMethods": [],
      "conceptIds": [
        "kampas"
      ],
      "formulaIds": [],
      "mistakeIds": [],
      "estimatedSeconds": 45
    },
    {
      "id": "lygios-ir-panasios-figuros-ex-016",
      "topicId": "lygios-ir-panasios-figuros",
      "grade": 6,
      "level": "hard",
      "type": "numericInput",
      "statement": "Lygios ir panašios figūros, mastelis ir trikampių lygumas: papildomas uždavinys Nr. 16.",
      "answer": {
        "kind": "numeric",
        "value": 16,
        "tolerance": 0
      },
      "hints": [
        {
          "order": 1,
          "text": "Pasirink tinkamą metodą.",
          "penalty": 0.1,
          "revealsConceptIds": [
            "kampas"
          ]
        }
      ],
      "solutionSteps": [
        {
          "text": "Papildomas pratimas.",
          "latex": "16"
        }
      ],
      "answerText": "16",
      "alternateMethods": [],
      "conceptIds": [
        "kampas"
      ],
      "formulaIds": [],
      "mistakeIds": [],
      "estimatedSeconds": 45
    },
    {
      "id": "lygios-ir-panasios-figuros-ex-017",
      "topicId": "lygios-ir-panasios-figuros",
      "grade": 6,
      "level": "hard",
      "type": "numericInput",
      "statement": "Lygios ir panašios figūros, mastelis ir trikampių lygumas: papildomas uždavinys Nr. 17.",
      "answer": {
        "kind": "numeric",
        "value": 17,
        "tolerance": 0
      },
      "hints": [
        {
          "order": 1,
          "text": "Pasirink tinkamą metodą.",
          "penalty": 0.1,
          "revealsConceptIds": [
            "kampas"
          ]
        }
      ],
      "solutionSteps": [
        {
          "text": "Papildomas pratimas.",
          "latex": "17"
        }
      ],
      "answerText": "17",
      "alternateMethods": [],
      "conceptIds": [
        "kampas"
      ],
      "formulaIds": [],
      "mistakeIds": [],
      "estimatedSeconds": 45
    },
    {
      "id": "lygios-ir-panasios-figuros-ex-018",
      "topicId": "lygios-ir-panasios-figuros",
      "grade": 6,
      "level": "hard",
      "type": "numericInput",
      "statement": "Lygios ir panašios figūros, mastelis ir trikampių lygumas: papildomas uždavinys Nr. 18.",
      "answer": {
        "kind": "numeric",
        "value": 18,
        "tolerance": 0
      },
      "hints": [
        {
          "order": 1,
          "text": "Pasirink tinkamą metodą.",
          "penalty": 0.1,
          "revealsConceptIds": [
            "kampas"
          ]
        }
      ],
      "solutionSteps": [
        {
          "text": "Papildomas pratimas.",
          "latex": "18"
        }
      ],
      "answerText": "18",
      "alternateMethods": [],
      "conceptIds": [
        "kampas"
      ],
      "formulaIds": [],
      "mistakeIds": [],
      "estimatedSeconds": 45
    },
    {
      "id": "lygios-ir-panasios-figuros-ex-019",
      "topicId": "lygios-ir-panasios-figuros",
      "grade": 6,
      "level": "hard",
      "type": "numericInput",
      "statement": "Lygios ir panašios figūros, mastelis ir trikampių lygumas: papildomas uždavinys Nr. 19.",
      "answer": {
        "kind": "numeric",
        "value": 19,
        "tolerance": 0
      },
      "hints": [
        {
          "order": 1,
          "text": "Pasirink tinkamą metodą.",
          "penalty": 0.1,
          "revealsConceptIds": [
            "kampas"
          ]
        }
      ],
      "solutionSteps": [
        {
          "text": "Papildomas pratimas.",
          "latex": "19"
        }
      ],
      "answerText": "19",
      "alternateMethods": [],
      "conceptIds": [
        "kampas"
      ],
      "formulaIds": [],
      "mistakeIds": [],
      "estimatedSeconds": 45
    },
    {
      "id": "lygios-ir-panasios-figuros-ex-020",
      "topicId": "lygios-ir-panasios-figuros",
      "grade": 6,
      "level": "hard",
      "type": "numericInput",
      "statement": "Lygios ir panašios figūros, mastelis ir trikampių lygumas: papildomas uždavinys Nr. 20.",
      "answer": {
        "kind": "numeric",
        "value": 20,
        "tolerance": 0
      },
      "hints": [
        {
          "order": 1,
          "text": "Pasirink tinkamą metodą.",
          "penalty": 0.1,
          "revealsConceptIds": [
            "kampas"
          ]
        }
      ],
      "solutionSteps": [
        {
          "text": "Papildomas pratimas.",
          "latex": "20"
        }
      ],
      "answerText": "20",
      "alternateMethods": [],
      "conceptIds": [
        "kampas"
      ],
      "formulaIds": [],
      "mistakeIds": [],
      "estimatedSeconds": 45
    }
  ],
  "tests": [
    {
      "id": "lygios-ir-panasios-figuros-test-topic",
      "title": "Lygios ir panašios figūros, mastelis ir trikampių lygumas testas",
      "scope": "topic",
      "topicIds": [
        "lygios-ir-panasios-figuros"
      ],
      "exerciseIds": [
        "lygios-ir-panasios-figuros-ex-001",
        "lygios-ir-panasios-figuros-ex-002",
        "lygios-ir-panasios-figuros-ex-003",
        "lygios-ir-panasios-figuros-ex-004",
        "lygios-ir-panasios-figuros-ex-005",
        "lygios-ir-panasios-figuros-ex-006",
        "lygios-ir-panasios-figuros-ex-007",
        "lygios-ir-panasios-figuros-ex-008"
      ],
      "masteryWeight": 1.2,
      "passingThreshold": 0.75,
      "timeLimitSeconds": 1800
    },
    {
      "id": "lygios-ir-panasios-figuros-test-challenge",
      "title": "Lygios ir panašios figūros, mastelis ir trikampių lygumas iššūkis",
      "scope": "topic",
      "topicIds": [
        "lygios-ir-panasios-figuros"
      ],
      "exerciseIds": [
        "lygios-ir-panasios-figuros-ex-009",
        "lygios-ir-panasios-figuros-ex-010",
        "lygios-ir-panasios-figuros-ex-011",
        "lygios-ir-panasios-figuros-ex-012",
        "lygios-ir-panasios-figuros-ex-013",
        "lygios-ir-panasios-figuros-ex-014",
        "lygios-ir-panasios-figuros-ex-015",
        "lygios-ir-panasios-figuros-ex-016"
      ],
      "masteryWeight": 1.6,
      "passingThreshold": 0.65,
      "timeLimitSeconds": 2400
    }
  ],
  "srsCards": [
    {
      "id": "lygios-ir-panasios-figuros-srs-kampas",
      "deck": "theory",
      "cardType": "concept",
      "front": "Kas yra kampas?",
      "back": "Dviejų spindulių arba tiesių susikirtimo dydis.",
      "conceptIds": [
        "kampas"
      ],
      "formulaIds": [],
      "mistakeIds": [],
      "defaultEnabled": true
    },
    {
      "id": "lygios-ir-panasios-figuros-srs-trikampis",
      "deck": "theory",
      "cardType": "concept",
      "front": "Kas yra trikampis?",
      "back": "Figūra iš trijų kraštinių ir trijų kampų.",
      "conceptIds": [
        "trikampis"
      ],
      "formulaIds": [],
      "mistakeIds": [],
      "defaultEnabled": true
    },
    {
      "id": "lygios-ir-panasios-figuros-srs-keturkampis",
      "deck": "theory",
      "cardType": "concept",
      "front": "Kas yra keturkampis?",
      "back": "Figūra iš keturių kraštinių.",
      "conceptIds": [
        "keturkampis"
      ],
      "formulaIds": [],
      "mistakeIds": [],
      "defaultEnabled": true
    },
    {
      "id": "lygios-ir-panasios-figuros-srs-perimetras",
      "deck": "theory",
      "cardType": "concept",
      "front": "Kas yra perimetras?",
      "back": "Kraštinių ilgių suma.",
      "conceptIds": [
        "perimetras"
      ],
      "formulaIds": [],
      "mistakeIds": [],
      "defaultEnabled": true
    },
    {
      "id": "lygios-ir-panasios-figuros-srs-trikampio-plotas",
      "deck": "practice",
      "cardType": "formula",
      "front": "Kas yra trikampio plotas?",
      "back": "Naudojama daugelyje ploto uždavinių.",
      "conceptIds": [
        "trikampio-plotas"
      ],
      "formulaIds": [],
      "mistakeIds": [],
      "defaultEnabled": true
    },
    {
      "id": "lygios-ir-panasios-figuros-srs-pitagoro-formule",
      "deck": "practice",
      "cardType": "formula",
      "front": "Kas yra pitagoro formulė?",
      "back": "Ryšys tarp stačiojo trikampio kraštinių.",
      "conceptIds": [
        "pitagoro-formule"
      ],
      "formulaIds": [],
      "mistakeIds": [],
      "defaultEnabled": true
    },
    {
      "id": "lygios-ir-panasios-figuros-srs-perimetra-supainioja-su-ploto-formule",
      "deck": "practice",
      "cardType": "mistake",
      "front": "Kas yra perimetrą supainioja su plotu?",
      "back": "Atskirk, ar reikia kraštinių sumos, ar užimamo ploto.",
      "conceptIds": [
        "perimetra-supainioja-su-ploto-formule"
      ],
      "formulaIds": [],
      "mistakeIds": [],
      "defaultEnabled": true
    },
    {
      "id": "lygios-ir-panasios-figuros-srs-pitagoro-teorema-netaikoma-ne-staciajame",
      "deck": "practice",
      "cardType": "mistake",
      "front": "Kas yra pitagoro teoremą taiko ne stačiajame trikampyje?",
      "back": "Pirmiausia patikrink, ar yra 90° kampas.",
      "conceptIds": [
        "pitagoro-teorema-netaikoma-ne-staciajame"
      ],
      "formulaIds": [],
      "mistakeIds": [],
      "defaultEnabled": true
    }
  ]
}